eoq3pyactions/__init__.py
eoq3pyactions/actionhandler/__init__.py
eoq3pyactions/actionhandler/action.py
eoq3pyactions/actionhandler/actionhandler.py
eoq3pyactions/actionhandler/job.py
eoq3pyactions/actionmanager/__init__.py
eoq3pyactions/actionmanager/actionmanager.py
eoq3pyactions/model/__init__.py
eoq3pyactions/model/actionmodeltopy.py
eoq3pyactions/model/actions.py
eoq3pyactions/util/__init__.py
eoq3pyactions/util/util.py
eoq3pyactions-3.1.0.dist-info/licenses/LICENSE
eoq3pyactions-3.1.0.dist-info/METADATA
eoq3pyactions-3.1.0.dist-info/WHEEL
eoq3pyactions-3.1.0.dist-info/top_level.txt
eoq3pyactions-3.1.0.dist-info/RECORD
