Metadata-Version: 2.4
Name: eoq3pyactions
Version: 3.1.0
Summary: action handler and python actions for EOQ3
Author-email: Bjoern Annighoefer <bjoern.annighoefer@ils.uni-stuttgart.de>
Project-URL: Homepage, https://gitlab.com/eoq/py/eoq3pyactions
Project-URL: Issues, https://gitlab.com/eoq/py/eoq3pyactions/-/issues
Classifier: Programming Language :: Python :: 3
Classifier: License :: OSI Approved :: MIT License
Classifier: Operating System :: OS Independent
Requires-Python: >=3.10
License-File: LICENSE
Requires-Dist: eoq3
Dynamic: license-file
